pygameiseg/__init__.py
pygameiseg/create_button.py
pygameiseasy-0.1.dist-info/LICENSE
pygameiseasy-0.1.dist-info/METADATA
pygameiseasy-0.1.dist-info/WHEEL
pygameiseasy-0.1.dist-info/top_level.txt
pygameiseasy-0.1.dist-info/RECORD
