Metadata-Version: 2.1
Name: pygameiseasy
Version: 0.1
Summary: A small package To Make pygame easy for beginers
Home-page: https://github.com/pypa/sampleproject
Author: vishnu01
Author-email: koharrupesh@gmail.com
Project-URL: Bug Tracker, https://github.com/pypa/sampleproject/issues
Classifier: Programming Language :: Python :: 3
Classifier: License :: OSI Approved :: MIT License
Classifier: Operating System :: OS Independent
Requires-Python: >=3.6
License-File: LICENSE
